CHANGES.txt
CONTRIBUTORS.txt
README.txt
TODO.txt
bootstrap.py
buildout.cfg
setup.cfg
setup.py
zest/__init__.py
zest.recipe.mysql.egg-info/PKG-INFO
zest.recipe.mysql.egg-info/SOURCES.txt
zest.recipe.mysql.egg-info/dependency_links.txt
zest.recipe.mysql.egg-info/entry_points.txt
zest.recipe.mysql.egg-info/namespace_packages.txt
zest.recipe.mysql.egg-info/not-zip-safe
zest.recipe.mysql.egg-info/requires.txt
zest.recipe.mysql.egg-info/top_level.txt
zest/recipe/__init__.py
zest/recipe/mysql/__init__.py