Metadata-Version: 1.0
Name: zest.recipe.mysql
Version: 1.0.4
Summary: A Buildout recipe to setup a MySQL database.
Home-page: https://svn.zestsoftware.nl/svn/zest/zest.recipe.mysql/trunk
Author: Jean-Paul Ladage
Author-email: j.ladage@zestsoftware.nl
License: ZPL
Keywords: buildout recipe mysql
Platform: UNKNOWN
Classifier: Framework :: Buildout
Classifier: Intended Audience :: Developers
Classifier: Topic :: Software Development :: Build Tools
Classifier: Topic :: Software Development :: Libraries :: Python Modules
Classifier: License :: OSI Approved :: Zope Public License
